seeker/__init__.py
seeker/seeker.1.0.0.cpython-310-darwin.so
seeker/seeker.1.0.0.cpython-311-darwin.so
seeker/seeker.1.0.0.cpython-38-darwin.so
seeker/seeker.1.0.0.cpython-39-darwin.so
seeker/seeker.py
insideopt-0.0.1.dist-info/AUTHORS.rst
insideopt-0.0.1.dist-info/LICENSE.rst
insideopt-0.0.1.dist-info/METADATA
insideopt-0.0.1.dist-info/WHEEL
insideopt-0.0.1.dist-info/top_level.txt
insideopt-0.0.1.dist-info/RECORD
