Metadata-Version: 2.1
Name: insideopt
Version: 0.0.1
Summary: InsideOpt Seeker Mac Distribution
Author: Meinolf Sellmann
Author-email: info@insideopt.com
Keywords: insideopt,seeker,optimization
Classifier: Development Status :: 5 - Production/Stable
Classifier: Intended Audience :: Developers
Classifier: Natural Language :: English
Classifier: Programming Language :: Python :: 3.8
Classifier: Programming Language :: Python :: 3.9
Classifier: Programming Language :: Python :: 3.10
Classifier: Programming Language :: Python :: 3.11
Classifier: Operating System :: MacOS :: MacOS X
Requires-Python: >=3.8.18
License-File: LICENSE.rst
License-File: AUTHORS.rst
